docxviewer/__init__.py
docxviewer/doc_viewer.py
docxviewer-0.0.6.dist-info/LICENSE.txt
docxviewer-0.0.6.dist-info/METADATA
docxviewer-0.0.6.dist-info/WHEEL
docxviewer-0.0.6.dist-info/entry_points.txt
docxviewer-0.0.6.dist-info/top_level.txt
docxviewer-0.0.6.dist-info/RECORD
