Metadata-Version: 2.1
Name: docxviewer
Version: 0.0.6
Summary: Tool for previewing multiple .docx files in a directory
Home-page: https://github.com/ehsong/docxviewer
Author: ['Eunhou Esther Song']
Author-email: eunhou.song@gmail.com
License: MIT
Platform: UNKNOWN
Requires-Dist: python-docx
Requires-Dist: ipython
Requires-Dist: Click
